uc/__init__.py
uc/conlib.py
uc/mesh.dll.2
uc/mesh.py
uc/mesh.so.2
uc/mlp.py
uc/plotting.py
uc/progress.py
uc-2.2.0.dist-info/METADATA
uc-2.2.0.dist-info/WHEEL
uc-2.2.0.dist-info/top_level.txt
uc-2.2.0.dist-info/RECORD
